{"time": "22:30:17.665245", "test_id": 0, "iter_cnt": 512, "latency (ms)": 74.987, "throughput (iters/s)": 6827.8502},
{"time": "22:30:17.865824", "test_id": 1, "iter_cnt": 512, "latency (ms)": 75.512, "throughput (iters/s)": 6780.3793},
{"time": "22:30:18.66345", "test_id": 2, "iter_cnt": 512, "latency (ms)": 75.979, "throughput (iters/s)": 6738.7041},
{"time": "22:30:18.265766", "test_id": 3, "iter_cnt": 512, "latency (ms)": 75.316, "throughput (iters/s)": 6798.0243},
{"time": "22:30:18.466413", "test_id": 4, "iter_cnt": 512, "latency (ms)": 75.877, "throughput (iters/s)": 6747.7628},
{"time": "22:30:18.666148", "test_id": 5, "iter_cnt": 512, "latency (ms)": 75.559, "throughput (iters/s)": 6776.1617},
{"time": "22:30:18.866039", "test_id": 6, "iter_cnt": 512, "latency (ms)": 75.396, "throughput (iters/s)": 6790.8112},
{"time": "22:30:19.66387", "test_id": 7, "iter_cnt": 512, "latency (ms)": 75.690, "throughput (iters/s)": 6764.4339},
{"time": "22:30:19.266579", "test_id": 8, "iter_cnt": 512, "latency (ms)": 75.830, "throughput (iters/s)": 6751.9451},
{"time": "22:30:19.467387", "test_id": 9, "iter_cnt": 512, "latency (ms)": 76.583, "throughput (iters/s)": 6685.5568},
{"time": "22:30:19.667503", "test_id": 10, "iter_cnt": 512, "latency (ms)": 76.645, "throughput (iters/s)": 6680.1487},
{"time": "22:30:19.867498", "test_id": 11, "iter_cnt": 512, "latency (ms)": 76.587, "throughput (iters/s)": 6685.2077},
{"time": "22:30:20.66899", "test_id": 12, "iter_cnt": 512, "latency (ms)": 75.933, "throughput (iters/s)": 6742.7864},
{"time": "22:30:20.266610", "test_id": 13, "iter_cnt": 512, "latency (ms)": 75.589, "throughput (iters/s)": 6773.4723},
{"time": "22:30:20.467479", "test_id": 14, "iter_cnt": 512, "latency (ms)": 76.404, "throughput (iters/s)": 6701.2198},
{"time": "22:30:20.666818", "test_id": 15, "iter_cnt": 512, "latency (ms)": 75.689, "throughput (iters/s)": 6764.5232},
{"time": "22:30:20.867512", "test_id": 16, "iter_cnt": 512, "latency (ms)": 76.299, "throughput (iters/s)": 6710.4418},
{"time": "22:30:21.67271", "test_id": 17, "iter_cnt": 512, "latency (ms)": 76.004, "throughput (iters/s)": 6736.4876},
{"time": "22:30:21.266797", "test_id": 18, "iter_cnt": 512, "latency (ms)": 75.476, "throughput (iters/s)": 6783.6133},
{"time": "22:30:21.468130", "test_id": 19, "iter_cnt": 512, "latency (ms)": 76.755, "throughput (iters/s)": 6670.5752},
{"time": "22:30:21.668253", "test_id": 20, "iter_cnt": 512, "latency (ms)": 76.825, "throughput (iters/s)": 6664.4972},
{"time": "22:30:21.867547", "test_id": 21, "iter_cnt": 512, "latency (ms)": 76.064, "throughput (iters/s)": 6731.1737},
{"time": "22:30:22.68940", "test_id": 22, "iter_cnt": 512, "latency (ms)": 77.373, "throughput (iters/s)": 6617.2954},
{"time": "22:30:22.268590", "test_id": 23, "iter_cnt": 512, "latency (ms)": 76.969, "throughput (iters/s)": 6652.0287},
{"time": "22:30:22.467761", "test_id": 24, "iter_cnt": 512, "latency (ms)": 76.086, "throughput (iters/s)": 6729.2275},
{"time": "22:30:22.668425", "test_id": 25, "iter_cnt": 512, "latency (ms)": 76.697, "throughput (iters/s)": 6675.6196},
{"time": "22:30:22.868999", "test_id": 26, "iter_cnt": 512, "latency (ms)": 77.188, "throughput (iters/s)": 6633.1554},
{"time": "22:30:23.68527", "test_id": 27, "iter_cnt": 512, "latency (ms)": 76.632, "throughput (iters/s)": 6681.2820},
{"time": "22:30:23.269690", "test_id": 28, "iter_cnt": 512, "latency (ms)": 77.741, "throughput (iters/s)": 6585.9714},
{"time": "22:30:23.467692", "test_id": 29, "iter_cnt": 512, "latency (ms)": 75.689, "throughput (iters/s)": 6764.5232},
{"time": "22:30:23.668755", "test_id": 30, "iter_cnt": 512, "latency (ms)": 76.698, "throughput (iters/s)": 6675.5326},
{"time": "22:30:23.868386", "test_id": 31, "iter_cnt": 512, "latency (ms)": 76.277, "throughput (iters/s)": 6712.3773},
{"time": "22:30:24.68538", "test_id": 32, "iter_cnt": 512, "latency (ms)": 76.375, "throughput (iters/s)": 6703.7643},
{"time": "22:30:24.268345", "test_id": 33, "iter_cnt": 512, "latency (ms)": 76.128, "throughput (iters/s)": 6725.5149},
{"time": "22:30:24.467969", "test_id": 34, "iter_cnt": 512, "latency (ms)": 75.698, "throughput (iters/s)": 6763.7190},
{"time": "22:30:24.668340", "test_id": 35, "iter_cnt": 512, "latency (ms)": 75.985, "throughput (iters/s)": 6738.1720},
{"time": "22:30:24.869737", "test_id": 36, "iter_cnt": 512, "latency (ms)": 77.328, "throughput (iters/s)": 6621.1463},
{"time": "22:30:25.69463", "test_id": 37, "iter_cnt": 512, "latency (ms)": 76.956, "throughput (iters/s)": 6653.1525},
{"time": "22:30:25.269598", "test_id": 38, "iter_cnt": 512, "latency (ms)": 77.037, "throughput (iters/s)": 6646.1570},
{"time": "22:30:25.470005", "test_id": 39, "iter_cnt": 512, "latency (ms)": 77.359, "throughput (iters/s)": 6618.4930},
{"time": "22:30:25.670118", "test_id": 40, "iter_cnt": 512, "latency (ms)": 77.389, "throughput (iters/s)": 6615.9273},
{"time": "22:30:25.870520", "test_id": 41, "iter_cnt": 512, "latency (ms)": 77.708, "throughput (iters/s)": 6588.7682},
{"time": "22:30:26.69255", "test_id": 42, "iter_cnt": 512, "latency (ms)": 76.391, "throughput (iters/s)": 6702.3602},
{"time": "22:30:26.269942", "test_id": 43, "iter_cnt": 512, "latency (ms)": 77.022, "throughput (iters/s)": 6647.4514},
{"time": "22:30:26.470189", "test_id": 44, "iter_cnt": 512, "latency (ms)": 77.184, "throughput (iters/s)": 6633.4992},
{"time": "22:30:26.670661", "test_id": 45, "iter_cnt": 512, "latency (ms)": 77.601, "throughput (iters/s)": 6597.8531},
{"time": "22:30:26.869558", "test_id": 46, "iter_cnt": 512, "latency (ms)": 76.444, "throughput (iters/s)": 6697.7134},
{"time": "22:30:27.71053", "test_id": 47, "iter_cnt": 512, "latency (ms)": 77.884, "throughput (iters/s)": 6573.8791},
{"time": "22:30:27.270418", "test_id": 48, "iter_cnt": 512, "latency (ms)": 77.196, "throughput (iters/s)": 6632.4680},
{"time": "22:30:27.470072", "test_id": 49, "iter_cnt": 512, "latency (ms)": 76.797, "throughput (iters/s)": 6666.9271},
{"time": "22:30:27.671105", "test_id": 50, "iter_cnt": 512, "latency (ms)": 77.776, "throughput (iters/s)": 6583.0076},
{"time": "22:30:27.870470", "test_id": 51, "iter_cnt": 512, "latency (ms)": 77.087, "throughput (iters/s)": 6641.8462},
{"time": "22:30:28.70460", "test_id": 52, "iter_cnt": 512, "latency (ms)": 77.024, "throughput (iters/s)": 6647.2788},
{"time": "22:30:28.270582", "test_id": 53, "iter_cnt": 512, "latency (ms)": 77.104, "throughput (iters/s)": 6640.3818},
{"time": "22:30:28.469642", "test_id": 54, "iter_cnt": 512, "latency (ms)": 76.110, "throughput (iters/s)": 6727.1055},
{"time": "22:30:28.671868", "test_id": 55, "iter_cnt": 512, "latency (ms)": 78.284, "throughput (iters/s)": 6540.2892},
{"time": "22:30:28.871048", "test_id": 56, "iter_cnt": 512, "latency (ms)": 77.409, "throughput (iters/s)": 6614.2180},
{"time": "22:30:29.70897", "test_id": 57, "iter_cnt": 512, "latency (ms)": 77.205, "throughput (iters/s)": 6631.6948},
{"time": "22:30:29.270821", "test_id": 58, "iter_cnt": 512, "latency (ms)": 77.076, "throughput (iters/s)": 6642.7941},
{"time": "22:30:29.470710", "test_id": 59, "iter_cnt": 512, "latency (ms)": 76.912, "throughput (iters/s)": 6656.9586},
{"time": "22:30:29.671049", "test_id": 60, "iter_cnt": 512, "latency (ms)": 77.197, "throughput (iters/s)": 6632.3821},
{"time": "22:30:29.870580", "test_id": 61, "iter_cnt": 512, "latency (ms)": 76.675, "throughput (iters/s)": 6677.5351},
{"time": "22:30:30.70516", "test_id": 62, "iter_cnt": 512, "latency (ms)": 76.558, "throughput (iters/s)": 6687.7400},
{"time": "22:30:30.271356", "test_id": 63, "iter_cnt": 512, "latency (ms)": 77.344, "throughput (iters/s)": 6619.7766},
{"time": "22:30:30.470735", "test_id": 64, "iter_cnt": 512, "latency (ms)": 76.670, "throughput (iters/s)": 6677.9705},
{"time": "22:30:30.671484", "test_id": 65, "iter_cnt": 512, "latency (ms)": 77.364, "throughput (iters/s)": 6618.0652},
{"time": "22:30:30.871349", "test_id": 66, "iter_cnt": 512, "latency (ms)": 77.176, "throughput (iters/s)": 6634.1868},
{"time": "22:30:31.72412", "test_id": 67, "iter_cnt": 512, "latency (ms)": 78.187, "throughput (iters/s)": 6548.4032},
{"time": "22:30:31.271448", "test_id": 68, "iter_cnt": 512, "latency (ms)": 77.169, "throughput (iters/s)": 6634.7886},
{"time": "22:30:31.470341", "test_id": 69, "iter_cnt": 512, "latency (ms)": 76.008, "throughput (iters/s)": 6736.1330},
{"time": "22:30:31.671596", "test_id": 70, "iter_cnt": 512, "latency (ms)": 77.209, "throughput (iters/s)": 6631.3513},
{"time": "22:30:31.870780", "test_id": 71, "iter_cnt": 512, "latency (ms)": 76.339, "throughput (iters/s)": 6706.9257},
{"time": "22:30:32.71431", "test_id": 72, "iter_cnt": 512, "latency (ms)": 76.937, "throughput (iters/s)": 6654.7955},
{"time": "22:30:32.271018", "test_id": 73, "iter_cnt": 512, "latency (ms)": 76.471, "throughput (iters/s)": 6695.3486},
{"time": "22:30:32.470601", "test_id": 74, "iter_cnt": 512, "latency (ms)": 76.000, "throughput (iters/s)": 6736.8421},
{"time": "22:30:32.671016", "test_id": 75, "iter_cnt": 512, "latency (ms)": 76.362, "throughput (iters/s)": 6704.9056},
{"time": "22:30:32.872735", "test_id": 76, "iter_cnt": 512, "latency (ms)": 78.027, "throughput (iters/s)": 6561.8312},
{"time": "22:30:33.70893", "test_id": 77, "iter_cnt": 512, "latency (ms)": 76.130, "throughput (iters/s)": 6725.3382},
{"time": "22:30:33.271263", "test_id": 78, "iter_cnt": 512, "latency (ms)": 76.446, "throughput (iters/s)": 6697.5381},
{"time": "22:30:33.471888", "test_id": 79, "iter_cnt": 512, "latency (ms)": 77.017, "throughput (iters/s)": 6647.8829},
{"time": "22:30:33.671449", "test_id": 80, "iter_cnt": 512, "latency (ms)": 76.523, "throughput (iters/s)": 6690.7988},
{"time": "22:30:33.871421", "test_id": 81, "iter_cnt": 512, "latency (ms)": 76.411, "throughput (iters/s)": 6700.6059},
{"time": "22:30:34.72427", "test_id": 82, "iter_cnt": 512, "latency (ms)": 77.363, "throughput (iters/s)": 6618.1508},
{"time": "22:30:34.272144", "test_id": 83, "iter_cnt": 512, "latency (ms)": 77.026, "throughput (iters/s)": 6647.1062},
{"time": "22:30:34.471257", "test_id": 84, "iter_cnt": 512, "latency (ms)": 76.085, "throughput (iters/s)": 6729.3159},
{"time": "22:30:34.671931", "test_id": 85, "iter_cnt": 512, "latency (ms)": 76.706, "throughput (iters/s)": 6674.8364},
{"time": "22:30:34.871539", "test_id": 86, "iter_cnt": 512, "latency (ms)": 76.260, "throughput (iters/s)": 6713.8736},
{"time": "22:30:35.72414", "test_id": 87, "iter_cnt": 512, "latency (ms)": 77.047, "throughput (iters/s)": 6645.2944},
{"time": "22:30:35.272223", "test_id": 88, "iter_cnt": 512, "latency (ms)": 76.801, "throughput (iters/s)": 6666.5799},
{"time": "22:30:35.471367", "test_id": 89, "iter_cnt": 512, "latency (ms)": 75.862, "throughput (iters/s)": 6749.0970},
{"time": "22:30:35.672284", "test_id": 90, "iter_cnt": 512, "latency (ms)": 76.692, "throughput (iters/s)": 6676.0549},
{"time": "22:30:35.871745", "test_id": 91, "iter_cnt": 512, "latency (ms)": 76.070, "throughput (iters/s)": 6730.6428},
{"time": "22:30:36.72827", "test_id": 92, "iter_cnt": 512, "latency (ms)": 77.098, "throughput (iters/s)": 6640.8986},
{"time": "22:30:36.271956", "test_id": 93, "iter_cnt": 512, "latency (ms)": 76.147, "throughput (iters/s)": 6723.8368},
{"time": "22:30:36.471517", "test_id": 94, "iter_cnt": 512, "latency (ms)": 75.624, "throughput (iters/s)": 6770.3375},
{"time": "22:30:36.672486", "test_id": 95, "iter_cnt": 512, "latency (ms)": 76.500, "throughput (iters/s)": 6692.8105},
{"time": "22:30:36.872441", "test_id": 96, "iter_cnt": 512, "latency (ms)": 76.370, "throughput (iters/s)": 6704.2032},
{"time": "22:30:37.72402", "test_id": 97, "iter_cnt": 512, "latency (ms)": 76.276, "throughput (iters/s)": 6712.4653},
{"time": "22:30:37.272082", "test_id": 98, "iter_cnt": 512, "latency (ms)": 75.901, "throughput (iters/s)": 6745.6292},
{"time": "22:30:37.472457", "test_id": 99, "iter_cnt": 512, "latency (ms)": 76.222, "throughput (iters/s)": 6717.2207},
{"time": "22:30:37.672696", "test_id": 100, "iter_cnt": 512, "latency (ms)": 76.381, "throughput (iters/s)": 6703.2377},
{"time": "22:30:37.872769", "test_id": 101, "iter_cnt": 512, "latency (ms)": 76.370, "throughput (iters/s)": 6704.2032},
{"time": "22:30:38.71887", "test_id": 102, "iter_cnt": 512, "latency (ms)": 75.405, "throughput (iters/s)": 6790.0007},
{"time": "22:30:38.271962", "test_id": 103, "iter_cnt": 512, "latency (ms)": 75.397, "throughput (iters/s)": 6790.7211},
{"time": "22:30:38.472393", "test_id": 104, "iter_cnt": 512, "latency (ms)": 75.773, "throughput (iters/s)": 6757.0243},
{"time": "22:30:38.672399", "test_id": 105, "iter_cnt": 512, "latency (ms)": 75.724, "throughput (iters/s)": 6761.3967},
{"time": "22:30:38.872483", "test_id": 106, "iter_cnt": 512, "latency (ms)": 75.755, "throughput (iters/s)": 6758.6298},
{"time": "22:30:39.73299", "test_id": 107, "iter_cnt": 512, "latency (ms)": 76.517, "throughput (iters/s)": 6691.3235},
{"time": "22:30:39.273224", "test_id": 108, "iter_cnt": 512, "latency (ms)": 76.353, "throughput (iters/s)": 6705.6959},
{"time": "22:30:39.473585", "test_id": 109, "iter_cnt": 512, "latency (ms)": 76.632, "throughput (iters/s)": 6681.2820},
{"time": "22:30:39.672768", "test_id": 110, "iter_cnt": 512, "latency (ms)": 75.732, "throughput (iters/s)": 6760.6824},
{"time": "22:30:39.873319", "test_id": 111, "iter_cnt": 512, "latency (ms)": 76.227, "throughput (iters/s)": 6716.7801},
{"time": "22:30:40.71964", "test_id": 112, "iter_cnt": 512, "latency (ms)": 74.792, "throughput (iters/s)": 6845.6519},
{"time": "22:30:40.274062", "test_id": 113, "iter_cnt": 512, "latency (ms)": 76.836, "throughput (iters/s)": 6663.5431},
{"time": "22:30:40.472476", "test_id": 114, "iter_cnt": 512, "latency (ms)": 75.196, "throughput (iters/s)": 6808.8728},
{"time": "22:30:40.673518", "test_id": 115, "iter_cnt": 512, "latency (ms)": 76.150, "throughput (iters/s)": 6723.5719},
{"time": "22:30:40.872962", "test_id": 116, "iter_cnt": 512, "latency (ms)": 75.510, "throughput (iters/s)": 6780.5589},
{"time": "22:30:41.73702", "test_id": 117, "iter_cnt": 512, "latency (ms)": 76.223, "throughput (iters/s)": 6717.1326},
{"time": "22:30:41.273161", "test_id": 118, "iter_cnt": 512, "latency (ms)": 75.629, "throughput (iters/s)": 6769.8899},
{"time": "22:30:41.472621", "test_id": 119, "iter_cnt": 512, "latency (ms)": 75.005, "throughput (iters/s)": 6826.2116},
{"time": "22:30:41.673636", "test_id": 120, "iter_cnt": 512, "latency (ms)": 75.934, "throughput (iters/s)": 6742.6976},
{"time": "22:30:41.873495", "test_id": 121, "iter_cnt": 512, "latency (ms)": 75.739, "throughput (iters/s)": 6760.0576},
{"time": "22:30:42.72947", "test_id": 122, "iter_cnt": 512, "latency (ms)": 75.137, "throughput (iters/s)": 6814.2194},
{"time": "22:30:42.274101", "test_id": 123, "iter_cnt": 512, "latency (ms)": 76.237, "throughput (iters/s)": 6715.8991},
{"time": "22:30:42.473619", "test_id": 124, "iter_cnt": 512, "latency (ms)": 75.675, "throughput (iters/s)": 6765.7747},
{"time": "22:30:42.673052", "test_id": 125, "iter_cnt": 512, "latency (ms)": 75.053, "throughput (iters/s)": 6821.8459},
{"time": "22:30:42.873054", "test_id": 126, "iter_cnt": 512, "latency (ms)": 75.002, "throughput (iters/s)": 6826.4846},
{"time": "22:30:43.73993", "test_id": 127, "iter_cnt": 512, "latency (ms)": 75.888, "throughput (iters/s)": 6746.7847},
{"time": "22:30:43.273252", "test_id": 128, "iter_cnt": 512, "latency (ms)": 75.093, "throughput (iters/s)": 6818.2121},
{"time": "22:30:43.473947", "test_id": 129, "iter_cnt": 512, "latency (ms)": 75.734, "throughput (iters/s)": 6760.5039},
{"time": "22:30:43.673969", "test_id": 130, "iter_cnt": 512, "latency (ms)": 75.701, "throughput (iters/s)": 6763.4509},
{"time": "22:30:43.873543", "test_id": 131, "iter_cnt": 512, "latency (ms)": 75.221, "throughput (iters/s)": 6806.6099},
{"time": "22:30:44.73323", "test_id": 132, "iter_cnt": 512, "latency (ms)": 74.947, "throughput (iters/s)": 6831.4943},
{"time": "22:30:44.273310", "test_id": 133, "iter_cnt": 512, "latency (ms)": 74.849, "throughput (iters/s)": 6840.4388},
{"time": "22:30:44.474297", "test_id": 134, "iter_cnt": 512, "latency (ms)": 75.782, "throughput (iters/s)": 6756.2218},
{"time": "22:30:44.673333", "test_id": 135, "iter_cnt": 512, "latency (ms)": 74.764, "throughput (iters/s)": 6848.2157},
{"time": "22:30:44.874047", "test_id": 136, "iter_cnt": 512, "latency (ms)": 75.424, "throughput (iters/s)": 6788.2902},
{"time": "22:30:45.73341", "test_id": 137, "iter_cnt": 512, "latency (ms)": 74.630, "throughput (iters/s)": 6860.5119},
{"time": "22:30:45.273970", "test_id": 138, "iter_cnt": 512, "latency (ms)": 75.205, "throughput (iters/s)": 6808.0580},
{"time": "22:30:45.473645", "test_id": 139, "iter_cnt": 512, "latency (ms)": 74.788, "throughput (iters/s)": 6846.0181},
{"time": "22:30:45.674170", "test_id": 140, "iter_cnt": 512, "latency (ms)": 75.228, "throughput (iters/s)": 6805.9765},
{"time": "22:30:45.873850", "test_id": 141, "iter_cnt": 512, "latency (ms)": 74.823, "throughput (iters/s)": 6842.8157},
{"time": "22:30:46.73624", "test_id": 142, "iter_cnt": 512, "latency (ms)": 74.543, "throughput (iters/s)": 6868.5188},
{"time": "22:30:46.274671", "test_id": 143, "iter_cnt": 512, "latency (ms)": 75.536, "throughput (iters/s)": 6778.2250},
{"time": "22:30:46.474024", "test_id": 144, "iter_cnt": 512, "latency (ms)": 74.807, "throughput (iters/s)": 6844.2793},
{"time": "22:30:46.674022", "test_id": 145, "iter_cnt": 512, "latency (ms)": 74.751, "throughput (iters/s)": 6849.4067},
{"time": "22:30:46.875108", "test_id": 146, "iter_cnt": 512, "latency (ms)": 75.784, "throughput (iters/s)": 6756.0435},
{"time": "22:30:47.75129", "test_id": 147, "iter_cnt": 512, "latency (ms)": 75.751, "throughput (iters/s)": 6758.9867},
{"time": "22:30:47.274180", "test_id": 148, "iter_cnt": 512, "latency (ms)": 74.718, "throughput (iters/s)": 6852.4318},
{"time": "22:30:47.474783", "test_id": 149, "iter_cnt": 512, "latency (ms)": 75.237, "throughput (iters/s)": 6805.1624},
{"time": "22:30:47.674411", "test_id": 150, "iter_cnt": 512, "latency (ms)": 74.811, "throughput (iters/s)": 6843.9133},
{"time": "22:30:47.874414", "test_id": 151, "iter_cnt": 512, "latency (ms)": 74.732, "throughput (iters/s)": 6851.1481},
{"time": "22:30:48.74632", "test_id": 152, "iter_cnt": 512, "latency (ms)": 74.896, "throughput (iters/s)": 6836.1461},
{"time": "22:30:48.274571", "test_id": 153, "iter_cnt": 512, "latency (ms)": 74.781, "throughput (iters/s)": 6846.6589},
{"time": "22:30:48.474921", "test_id": 154, "iter_cnt": 512, "latency (ms)": 75.076, "throughput (iters/s)": 6819.7560},
{"time": "22:30:48.674888", "test_id": 155, "iter_cnt": 512, "latency (ms)": 74.989, "throughput (iters/s)": 6827.6681},
{"time": "22:30:48.875561", "test_id": 156, "iter_cnt": 512, "latency (ms)": 75.607, "throughput (iters/s)": 6771.8597},
{"time": "22:30:49.75158", "test_id": 157, "iter_cnt": 512, "latency (ms)": 75.122, "throughput (iters/s)": 6815.5800},
{"time": "22:30:49.274790", "test_id": 158, "iter_cnt": 512, "latency (ms)": 74.699, "throughput (iters/s)": 6854.1748},
{"time": "22:30:49.475084", "test_id": 159, "iter_cnt": 512, "latency (ms)": 74.940, "throughput (iters/s)": 6832.1324},
{"time": "22:30:49.675243", "test_id": 160, "iter_cnt": 512, "latency (ms)": 75.045, "throughput (iters/s)": 6822.5731},
{"time": "22:30:49.875228", "test_id": 161, "iter_cnt": 512, "latency (ms)": 74.977, "throughput (iters/s)": 6828.7608},
{"time": "22:30:50.75475", "test_id": 162, "iter_cnt": 512, "latency (ms)": 75.170, "throughput (iters/s)": 6811.2279},
{"time": "22:30:50.275692", "test_id": 163, "iter_cnt": 512, "latency (ms)": 75.334, "throughput (iters/s)": 6796.4000},
{"time": "22:30:50.475056", "test_id": 164, "iter_cnt": 512, "latency (ms)": 74.643, "throughput (iters/s)": 6859.3170},
{"time": "22:30:50.675133", "test_id": 165, "iter_cnt": 512, "latency (ms)": 74.666, "throughput (iters/s)": 6857.2041},
{"time": "22:30:50.875156", "test_id": 166, "iter_cnt": 512, "latency (ms)": 74.651, "throughput (iters/s)": 6858.5819},
{"time": "22:30:51.75430", "test_id": 167, "iter_cnt": 512, "latency (ms)": 74.870, "throughput (iters/s)": 6838.5201},
{"time": "22:30:51.275667", "test_id": 168, "iter_cnt": 512, "latency (ms)": 75.023, "throughput (iters/s)": 6824.5738},
{"time": "22:30:51.475950", "test_id": 169, "iter_cnt": 512, "latency (ms)": 75.221, "throughput (iters/s)": 6806.6099},
{"time": "22:30:51.675552", "test_id": 170, "iter_cnt": 512, "latency (ms)": 74.739, "throughput (iters/s)": 6850.5064},
{"time": "22:30:51.875933", "test_id": 171, "iter_cnt": 512, "latency (ms)": 75.034, "throughput (iters/s)": 6823.5733},
{"time": "22:30:52.76417", "test_id": 172, "iter_cnt": 512, "latency (ms)": 75.424, "throughput (iters/s)": 6788.2902},
{"time": "22:30:52.276349", "test_id": 173, "iter_cnt": 512, "latency (ms)": 75.301, "throughput (iters/s)": 6799.3785},
{"time": "22:30:52.476339", "test_id": 174, "iter_cnt": 512, "latency (ms)": 75.237, "throughput (iters/s)": 6805.1624},
{"time": "22:30:52.676344", "test_id": 175, "iter_cnt": 512, "latency (ms)": 75.160, "throughput (iters/s)": 6812.1341},
{"time": "22:30:52.876275", "test_id": 176, "iter_cnt": 512, "latency (ms)": 75.007, "throughput (iters/s)": 6826.0296},
{"time": "22:30:53.76493", "test_id": 177, "iter_cnt": 512, "latency (ms)": 75.142, "throughput (iters/s)": 6813.7659},
{"time": "22:30:53.277013", "test_id": 178, "iter_cnt": 512, "latency (ms)": 75.607, "throughput (iters/s)": 6771.8597},
{"time": "22:30:53.476664", "test_id": 179, "iter_cnt": 512, "latency (ms)": 75.205, "throughput (iters/s)": 6808.0580},
{"time": "22:30:53.677373", "test_id": 180, "iter_cnt": 512, "latency (ms)": 75.830, "throughput (iters/s)": 6751.9451},
{"time": "22:30:53.877635", "test_id": 181, "iter_cnt": 512, "latency (ms)": 76.037, "throughput (iters/s)": 6733.5639},
{"time": "22:30:54.76589", "test_id": 182, "iter_cnt": 512, "latency (ms)": 74.937, "throughput (iters/s)": 6832.4059},
{"time": "22:30:54.277042", "test_id": 183, "iter_cnt": 512, "latency (ms)": 75.298, "throughput (iters/s)": 6799.6494},
{"time": "22:30:54.477182", "test_id": 184, "iter_cnt": 512, "latency (ms)": 75.384, "throughput (iters/s)": 6791.8922},
{"time": "22:30:54.676955", "test_id": 185, "iter_cnt": 512, "latency (ms)": 75.104, "throughput (iters/s)": 6817.2135},
{"time": "22:30:54.877066", "test_id": 186, "iter_cnt": 512, "latency (ms)": 75.159, "throughput (iters/s)": 6812.2248},
{"time": "22:30:55.77307", "test_id": 187, "iter_cnt": 512, "latency (ms)": 75.346, "throughput (iters/s)": 6795.3176},
{"time": "22:30:55.277297", "test_id": 188, "iter_cnt": 512, "latency (ms)": 75.253, "throughput (iters/s)": 6803.7155},
{"time": "22:30:55.477876", "test_id": 189, "iter_cnt": 512, "latency (ms)": 75.777, "throughput (iters/s)": 6756.6676},
{"time": "22:30:55.677777", "test_id": 190, "iter_cnt": 512, "latency (ms)": 75.625, "throughput (iters/s)": 6770.2479},
{"time": "22:30:55.877383", "test_id": 191, "iter_cnt": 512, "latency (ms)": 75.178, "throughput (iters/s)": 6810.5031},
{"time": "22:30:56.77712", "test_id": 192, "iter_cnt": 512, "latency (ms)": 75.453, "throughput (iters/s)": 6785.6812},
{"time": "22:30:56.278397", "test_id": 193, "iter_cnt": 512, "latency (ms)": 76.085, "throughput (iters/s)": 6729.3159},
{"time": "22:30:56.477931", "test_id": 194, "iter_cnt": 512, "latency (ms)": 75.534, "throughput (iters/s)": 6778.4044},
{"time": "22:30:56.678188", "test_id": 195, "iter_cnt": 512, "latency (ms)": 75.707, "throughput (iters/s)": 6762.9149},
{"time": "22:30:56.879093", "test_id": 196, "iter_cnt": 512, "latency (ms)": 76.528, "throughput (iters/s)": 6690.3617},
{"time": "22:30:57.78198", "test_id": 197, "iter_cnt": 512, "latency (ms)": 75.575, "throughput (iters/s)": 6774.7271},
{"time": "22:30:57.278766", "test_id": 198, "iter_cnt": 512, "latency (ms)": 76.090, "throughput (iters/s)": 6728.8737},
{"time": "22:30:57.478532", "test_id": 199, "iter_cnt": 512, "latency (ms)": 75.766, "throughput (iters/s)": 6757.6485},
{"time": "22:30:57.679138", "test_id": 200, "iter_cnt": 512, "latency (ms)": 76.288, "throughput (iters/s)": 6711.4094},
{"time": "22:30:57.878765", "test_id": 201, "iter_cnt": 512, "latency (ms)": 75.798, "throughput (iters/s)": 6754.7956},
{"time": "22:30:58.78828", "test_id": 202, "iter_cnt": 512, "latency (ms)": 75.777, "throughput (iters/s)": 6756.6676},
{"time": "22:30:58.278751", "test_id": 203, "iter_cnt": 512, "latency (ms)": 75.619, "throughput (iters/s)": 6770.7851},
{"time": "22:30:58.478747", "test_id": 204, "iter_cnt": 512, "latency (ms)": 75.561, "throughput (iters/s)": 6775.9823},
{"time": "22:30:58.679332", "test_id": 205, "iter_cnt": 512, "latency (ms)": 76.034, "throughput (iters/s)": 6733.8296},
{"time": "22:30:58.879588", "test_id": 206, "iter_cnt": 512, "latency (ms)": 76.229, "throughput (iters/s)": 6716.6039},
{"time": "22:30:59.79199", "test_id": 207, "iter_cnt": 512, "latency (ms)": 75.786, "throughput (iters/s)": 6755.8652},
{"time": "22:30:59.279253", "test_id": 208, "iter_cnt": 512, "latency (ms)": 75.785, "throughput (iters/s)": 6755.9543},
{"time": "22:30:59.479625", "test_id": 209, "iter_cnt": 512, "latency (ms)": 76.042, "throughput (iters/s)": 6733.1212},
{"time": "22:30:59.679633", "test_id": 210, "iter_cnt": 512, "latency (ms)": 75.996, "throughput (iters/s)": 6737.1967},
{"time": "22:30:59.880396", "test_id": 211, "iter_cnt": 512, "latency (ms)": 76.705, "throughput (iters/s)": 6674.9234},
{"time": "22:31:00.79682", "test_id": 212, "iter_cnt": 512, "latency (ms)": 75.920, "throughput (iters/s)": 6743.9410},
{"time": "22:31:00.279965", "test_id": 213, "iter_cnt": 512, "latency (ms)": 76.149, "throughput (iters/s)": 6723.6602},
{"time": "22:31:00.480200", "test_id": 214, "iter_cnt": 512, "latency (ms)": 76.298, "throughput (iters/s)": 6710.5298},
{"time": "22:31:00.680032", "test_id": 215, "iter_cnt": 512, "latency (ms)": 76.041, "throughput (iters/s)": 6733.2097},
{"time": "22:31:00.880612", "test_id": 216, "iter_cnt": 512, "latency (ms)": 76.534, "throughput (iters/s)": 6689.8372},
{"time": "22:31:01.80451", "test_id": 217, "iter_cnt": 512, "latency (ms)": 76.288, "throughput (iters/s)": 6711.4094},
{"time": "22:31:01.281880", "test_id": 218, "iter_cnt": 512, "latency (ms)": 77.633, "throughput (iters/s)": 6595.1335},
{"time": "22:31:01.480747", "test_id": 219, "iter_cnt": 512, "latency (ms)": 76.415, "throughput (iters/s)": 6700.2552},
{"time": "22:31:01.680153", "test_id": 220, "iter_cnt": 512, "latency (ms)": 75.737, "throughput (iters/s)": 6760.2361},
{"time": "22:31:01.880622", "test_id": 221, "iter_cnt": 512, "latency (ms)": 76.152, "throughput (iters/s)": 6723.3953},
{"time": "22:31:02.82187", "test_id": 222, "iter_cnt": 512, "latency (ms)": 77.633, "throughput (iters/s)": 6595.1335},
{"time": "22:31:02.281321", "test_id": 223, "iter_cnt": 512, "latency (ms)": 76.712, "throughput (iters/s)": 6674.3143},
{"time": "22:31:02.480626", "test_id": 224, "iter_cnt": 512, "latency (ms)": 75.963, "throughput (iters/s)": 6740.1235},
{"time": "22:31:02.682543", "test_id": 225, "iter_cnt": 512, "latency (ms)": 77.825, "throughput (iters/s)": 6578.8628},
{"time": "22:31:02.881975", "test_id": 226, "iter_cnt": 512, "latency (ms)": 77.203, "throughput (iters/s)": 6631.8666},
{"time": "22:31:03.80755", "test_id": 227, "iter_cnt": 512, "latency (ms)": 75.929, "throughput (iters/s)": 6743.1416},
{"time": "22:31:03.282427", "test_id": 228, "iter_cnt": 512, "latency (ms)": 77.546, "throughput (iters/s)": 6602.5327},
{"time": "22:31:03.481113", "test_id": 229, "iter_cnt": 512, "latency (ms)": 76.178, "throughput (iters/s)": 6721.1006},
{"time": "22:31:03.682734", "test_id": 230, "iter_cnt": 512, "latency (ms)": 77.745, "throughput (iters/s)": 6585.6325},
{"time": "22:31:03.881661", "test_id": 231, "iter_cnt": 512, "latency (ms)": 76.619, "throughput (iters/s)": 6682.4156},
{"time": "22:31:04.82101", "test_id": 232, "iter_cnt": 512, "latency (ms)": 77.006, "throughput (iters/s)": 6648.8326},
{"time": "22:31:04.281522", "test_id": 233, "iter_cnt": 512, "latency (ms)": 76.373, "throughput (iters/s)": 6703.9399},
{"time": "22:31:04.482969", "test_id": 234, "iter_cnt": 512, "latency (ms)": 77.736, "throughput (iters/s)": 6586.3950},
{"time": "22:31:04.681869", "test_id": 235, "iter_cnt": 512, "latency (ms)": 76.582, "throughput (iters/s)": 6685.6441},
{"time": "22:31:04.882160", "test_id": 236, "iter_cnt": 512, "latency (ms)": 76.786, "throughput (iters/s)": 6667.8822},
{"time": "22:31:05.83842", "test_id": 237, "iter_cnt": 512, "latency (ms)": 78.413, "throughput (iters/s)": 6529.5295},
{"time": "22:31:05.282185", "test_id": 238, "iter_cnt": 512, "latency (ms)": 76.664, "throughput (iters/s)": 6678.4932},
{"time": "22:31:05.483428", "test_id": 239, "iter_cnt": 512, "latency (ms)": 77.855, "throughput (iters/s)": 6576.3278},
{"time": "22:31:05.682979", "test_id": 240, "iter_cnt": 512, "latency (ms)": 77.321, "throughput (iters/s)": 6621.7457},
{"time": "22:31:05.882406", "test_id": 241, "iter_cnt": 512, "latency (ms)": 76.663, "throughput (iters/s)": 6678.5803},
{"time": "22:31:06.84140", "test_id": 242, "iter_cnt": 512, "latency (ms)": 78.312, "throughput (iters/s)": 6537.9508},
{"time": "22:31:06.283223", "test_id": 243, "iter_cnt": 512, "latency (ms)": 77.341, "throughput (iters/s)": 6620.0334},
{"time": "22:31:06.483394", "test_id": 244, "iter_cnt": 512, "latency (ms)": 77.458, "throughput (iters/s)": 6610.0338},
{"time": "22:31:06.682842", "test_id": 245, "iter_cnt": 512, "latency (ms)": 76.822, "throughput (iters/s)": 6664.7575},
{"time": "22:31:06.883004", "test_id": 246, "iter_cnt": 512, "latency (ms)": 76.899, "throughput (iters/s)": 6658.0840},
{"time": "22:31:07.85215", "test_id": 247, "iter_cnt": 512, "latency (ms)": 79.027, "throughput (iters/s)": 6478.7984},
{"time": "22:31:07.283430", "test_id": 248, "iter_cnt": 512, "latency (ms)": 77.162, "throughput (iters/s)": 6635.3905},
{"time": "22:31:07.483097", "test_id": 249, "iter_cnt": 512, "latency (ms)": 76.745, "throughput (iters/s)": 6671.4444},
{"time": "22:31:07.684915", "test_id": 250, "iter_cnt": 512, "latency (ms)": 78.508, "throughput (iters/s)": 6521.6284},
{"time": "22:31:07.883409", "test_id": 251, "iter_cnt": 512, "latency (ms)": 76.921, "throughput (iters/s)": 6656.1797},
{"time": "22:31:08.84564", "test_id": 252, "iter_cnt": 512, "latency (ms)": 77.992, "throughput (iters/s)": 6564.7759},
{"time": "22:31:08.284588", "test_id": 253, "iter_cnt": 512, "latency (ms)": 77.932, "throughput (iters/s)": 6569.8301},
{"time": "22:31:08.484176", "test_id": 254, "iter_cnt": 512, "latency (ms)": 77.465, "throughput (iters/s)": 6609.4365},
{"time": "22:31:08.683922", "test_id": 255, "iter_cnt": 512, "latency (ms)": 77.127, "throughput (iters/s)": 6638.4016},
{"time": "22:31:08.885985", "test_id": 256, "iter_cnt": 512, "latency (ms)": 79.106, "throughput (iters/s)": 6472.3283},
{"time": "22:31:09.84262", "test_id": 257, "iter_cnt": 512, "latency (ms)": 77.300, "throughput (iters/s)": 6623.5446},
{"time": "22:31:09.284952", "test_id": 258, "iter_cnt": 512, "latency (ms)": 77.905, "throughput (iters/s)": 6572.1071},
{"time": "22:31:09.485522", "test_id": 259, "iter_cnt": 512, "latency (ms)": 78.390, "throughput (iters/s)": 6531.4453},
{"time": "22:31:09.685129", "test_id": 260, "iter_cnt": 512, "latency (ms)": 77.943, "throughput (iters/s)": 6568.9029},
{"time": "22:31:09.884087", "test_id": 261, "iter_cnt": 512, "latency (ms)": 76.847, "throughput (iters/s)": 6662.5893},
{"time": "22:31:10.86681", "test_id": 262, "iter_cnt": 512, "latency (ms)": 79.357, "throughput (iters/s)": 6451.8568},
{"time": "22:31:10.285078", "test_id": 263, "iter_cnt": 512, "latency (ms)": 77.667, "throughput (iters/s)": 6592.2464},
{"time": "22:31:10.484994", "test_id": 264, "iter_cnt": 512, "latency (ms)": 77.499, "throughput (iters/s)": 6606.5369},
{"time": "22:31:10.686031", "test_id": 265, "iter_cnt": 512, "latency (ms)": 78.453, "throughput (iters/s)": 6526.2004},
{"time": "22:31:10.885968", "test_id": 266, "iter_cnt": 512, "latency (ms)": 78.307, "throughput (iters/s)": 6538.3682},
{"time": "22:31:11.84947", "test_id": 267, "iter_cnt": 512, "latency (ms)": 77.203, "throughput (iters/s)": 6631.8666},
{"time": "22:31:11.286179", "test_id": 268, "iter_cnt": 512, "latency (ms)": 78.381, "throughput (iters/s)": 6532.1953},
{"time": "22:31:11.486699", "test_id": 269, "iter_cnt": 512, "latency (ms)": 78.846, "throughput (iters/s)": 6493.6712},
{"time": "22:31:11.685139", "test_id": 270, "iter_cnt": 512, "latency (ms)": 77.233, "throughput (iters/s)": 6629.2906},
{"time": "22:31:11.885360", "test_id": 271, "iter_cnt": 512, "latency (ms)": 77.369, "throughput (iters/s)": 6617.6376},
{"time": "22:31:12.87559", "test_id": 272, "iter_cnt": 512, "latency (ms)": 79.514, "throughput (iters/s)": 6439.1176},
{"time": "22:31:12.286614", "test_id": 273, "iter_cnt": 512, "latency (ms)": 78.515, "throughput (iters/s)": 6521.0469},
{"time": "22:31:12.486882", "test_id": 274, "iter_cnt": 512, "latency (ms)": 78.728, "throughput (iters/s)": 6503.4041},
{"time": "22:31:12.686394", "test_id": 275, "iter_cnt": 512, "latency (ms)": 78.156, "throughput (iters/s)": 6551.0006},
{"time": "22:31:12.886765", "test_id": 276, "iter_cnt": 512, "latency (ms)": 78.473, "throughput (iters/s)": 6524.5371},
{"time": "22:31:13.87109", "test_id": 277, "iter_cnt": 512, "latency (ms)": 78.735, "throughput (iters/s)": 6502.8259},
{"time": "22:31:13.285780", "test_id": 278, "iter_cnt": 512, "latency (ms)": 77.322, "throughput (iters/s)": 6621.6601},
{"time": "22:31:13.488974", "test_id": 279, "iter_cnt": 512, "latency (ms)": 80.431, "throughput (iters/s)": 6365.7048},
{"time": "22:31:13.687688", "test_id": 280, "iter_cnt": 512, "latency (ms)": 79.057, "throughput (iters/s)": 6476.3399},
{"time": "22:31:13.886283", "test_id": 281, "iter_cnt": 512, "latency (ms)": 77.562, "throughput (iters/s)": 6601.1707},
{"time": "22:31:14.87726", "test_id": 282, "iter_cnt": 512, "latency (ms)": 78.921, "throughput (iters/s)": 6487.5002},
{"time": "22:31:14.288916", "test_id": 283, "iter_cnt": 512, "latency (ms)": 80.057, "throughput (iters/s)": 6395.4432},
{"time": "22:31:14.486882", "test_id": 284, "iter_cnt": 512, "latency (ms)": 77.938, "throughput (iters/s)": 6569.3243},
{"time": "22:31:14.689423", "test_id": 285, "iter_cnt": 512, "latency (ms)": 80.425, "throughput (iters/s)": 6366.1797},
{"time": "22:31:14.887440", "test_id": 286, "iter_cnt": 512, "latency (ms)": 78.387, "throughput (iters/s)": 6531.6953},
{"time": "22:31:15.88543", "test_id": 287, "iter_cnt": 512, "latency (ms)": 79.403, "throughput (iters/s)": 6448.1191},
{"time": "22:31:15.289106", "test_id": 288, "iter_cnt": 512, "latency (ms)": 79.912, "throughput (iters/s)": 6407.0478},
{"time": "22:31:15.487076", "test_id": 289, "iter_cnt": 512, "latency (ms)": 77.828, "throughput (iters/s)": 6578.6092},
{"time": "22:31:15.688688", "test_id": 290, "iter_cnt": 512, "latency (ms)": 79.386, "throughput (iters/s)": 6449.4999},
{"time": "22:31:15.888113", "test_id": 291, "iter_cnt": 512, "latency (ms)": 78.722, "throughput (iters/s)": 6503.8998},
{"time": "22:31:16.87297", "test_id": 292, "iter_cnt": 512, "latency (ms)": 77.820, "throughput (iters/s)": 6579.2855},
{"time": "22:31:16.288372", "test_id": 293, "iter_cnt": 512, "latency (ms)": 78.840, "throughput (iters/s)": 6494.1654},
{"time": "22:31:16.488864", "test_id": 294, "iter_cnt": 512, "latency (ms)": 79.278, "throughput (iters/s)": 6458.2860},
{"time": "22:31:16.688357", "test_id": 295, "iter_cnt": 512, "latency (ms)": 78.687, "throughput (iters/s)": 6506.7927},
{"time": "22:31:16.887514", "test_id": 296, "iter_cnt": 512, "latency (ms)": 77.791, "throughput (iters/s)": 6581.7382},
{"time": "22:31:17.89826", "test_id": 297, "iter_cnt": 512, "latency (ms)": 80.049, "throughput (iters/s)": 6396.0824},
{"time": "22:31:17.290432", "test_id": 298, "iter_cnt": 512, "latency (ms)": 80.569, "throughput (iters/s)": 6354.8015},
{"time": "22:31:17.488146", "test_id": 299, "iter_cnt": 512, "latency (ms)": 78.228, "throughput (iters/s)": 6544.9711},
{"time": "22:31:17.691106", "test_id": 300, "iter_cnt": 512, "latency (ms)": 81.104, "throughput (iters/s)": 6312.8822},
{"time": "22:31:17.888615", "test_id": 301, "iter_cnt": 512, "latency (ms)": 78.528, "throughput (iters/s)": 6519.9674},
{"time": "22:31:18.87882", "test_id": 302, "iter_cnt": 512, "latency (ms)": 77.711, "throughput (iters/s)": 6588.5139},
{"time": "22:31:18.290413", "test_id": 303, "iter_cnt": 512, "latency (ms)": 80.156, "throughput (iters/s)": 6387.5443},
{"time": "22:31:18.489608", "test_id": 304, "iter_cnt": 512, "latency (ms)": 79.297, "throughput (iters/s)": 6456.7386},
{"time": "22:31:18.688635", "test_id": 305, "iter_cnt": 512, "latency (ms)": 78.269, "throughput (iters/s)": 6541.5426},
{"time": "22:31:18.889606", "test_id": 306, "iter_cnt": 512, "latency (ms)": 79.187, "throughput (iters/s)": 6465.7078},
{"time": "22:31:19.88674", "test_id": 307, "iter_cnt": 512, "latency (ms)": 78.200, "throughput (iters/s)": 6547.3146},
{"time": "22:31:19.289092", "test_id": 308, "iter_cnt": 512, "latency (ms)": 78.523, "throughput (iters/s)": 6520.3826},
{"time": "22:31:19.491457", "test_id": 309, "iter_cnt": 512, "latency (ms)": 80.833, "throughput (iters/s)": 6334.0467},
{"time": "22:31:19.689445", "test_id": 310, "iter_cnt": 512, "latency (ms)": 78.738, "throughput (iters/s)": 6502.5782},
{"time": "22:31:19.888836", "test_id": 311, "iter_cnt": 512, "latency (ms)": 78.074, "throughput (iters/s)": 6557.8810},
{"time": "22:31:20.89448", "test_id": 312, "iter_cnt": 512, "latency (ms)": 78.603, "throughput (iters/s)": 6513.7463},
{"time": "22:31:20.290848", "test_id": 313, "iter_cnt": 512, "latency (ms)": 79.949, "throughput (iters/s)": 6404.0826},
{"time": "22:31:20.489427", "test_id": 314, "iter_cnt": 512, "latency (ms)": 78.473, "throughput (iters/s)": 6524.5371},
{"time": "22:31:20.689525", "test_id": 315, "iter_cnt": 512, "latency (ms)": 78.517, "throughput (iters/s)": 6520.8808},
{"time": "22:31:20.891740", "test_id": 316, "iter_cnt": 512, "latency (ms)": 80.678, "throughput (iters/s)": 6346.2158},
{"time": "22:31:21.90050", "test_id": 317, "iter_cnt": 512, "latency (ms)": 78.935, "throughput (iters/s)": 6486.3495},
{"time": "22:31:21.288821", "test_id": 318, "iter_cnt": 512, "latency (ms)": 77.651, "throughput (iters/s)": 6593.6047},
{"time": "22:31:21.494149", "test_id": 319, "iter_cnt": 512, "latency (ms)": 82.925, "throughput (iters/s)": 6174.2538},
{"time": "22:31:21.690757", "test_id": 320, "iter_cnt": 512, "latency (ms)": 79.480, "throughput (iters/s)": 6441.8722},
{"time": "22:31:21.890295", "test_id": 321, "iter_cnt": 512, "latency (ms)": 78.964, "throughput (iters/s)": 6483.9674},
{"time": "22:31:22.89675", "test_id": 322, "iter_cnt": 512, "latency (ms)": 78.290, "throughput (iters/s)": 6539.7880},
{"time": "22:31:22.290821", "test_id": 323, "iter_cnt": 512, "latency (ms)": 79.383, "throughput (iters/s)": 6449.7436},
{"time": "22:31:22.489812", "test_id": 324, "iter_cnt": 512, "latency (ms)": 78.320, "throughput (iters/s)": 6537.2829},
{"time": "22:31:22.691720", "test_id": 325, "iter_cnt": 512, "latency (ms)": 80.176, "throughput (iters/s)": 6385.9509},
{"time": "22:31:22.889989", "test_id": 326, "iter_cnt": 512, "latency (ms)": 78.391, "throughput (iters/s)": 6531.3620},
{"time": "22:31:23.90204", "test_id": 327, "iter_cnt": 512, "latency (ms)": 78.552, "throughput (iters/s)": 6517.9754},
{"time": "22:31:23.290216", "test_id": 328, "iter_cnt": 512, "latency (ms)": 78.479, "throughput (iters/s)": 6524.0383},
{"time": "22:31:23.492699", "test_id": 329, "iter_cnt": 512, "latency (ms)": 80.883, "throughput (iters/s)": 6330.1312},
{"time": "22:31:23.690571", "test_id": 330, "iter_cnt": 512, "latency (ms)": 78.671, "throughput (iters/s)": 6508.1161},
{"time": "22:31:23.890476", "test_id": 331, "iter_cnt": 512, "latency (ms)": 78.522, "throughput (iters/s)": 6520.4656},
{"time": "22:31:24.91486", "test_id": 332, "iter_cnt": 512, "latency (ms)": 79.479, "throughput (iters/s)": 6441.9532},
{"time": "22:31:24.291234", "test_id": 333, "iter_cnt": 512, "latency (ms)": 79.142, "throughput (iters/s)": 6469.3841},
{"time": "22:31:24.491152", "test_id": 334, "iter_cnt": 512, "latency (ms)": 78.977, "throughput (iters/s)": 6482.9001},
{"time": "22:31:24.690780", "test_id": 335, "iter_cnt": 512, "latency (ms)": 78.521, "throughput (iters/s)": 6520.5486},
{"time": "22:31:24.891880", "test_id": 336, "iter_cnt": 512, "latency (ms)": 79.537, "throughput (iters/s)": 6437.2556},
{"time": "22:31:25.92972", "test_id": 337, "iter_cnt": 512, "latency (ms)": 80.540, "throughput (iters/s)": 6357.0896},
{"time": "22:31:25.292331", "test_id": 338, "iter_cnt": 512, "latency (ms)": 79.845, "throughput (iters/s)": 6412.4241},
{"time": "22:31:25.490868", "test_id": 339, "iter_cnt": 512, "latency (ms)": 78.298, "throughput (iters/s)": 6539.1198},
{"time": "22:31:25.692181", "test_id": 340, "iter_cnt": 512, "latency (ms)": 79.528, "throughput (iters/s)": 6437.9841},
{"time": "22:31:25.891713", "test_id": 341, "iter_cnt": 512, "latency (ms)": 78.974, "throughput (iters/s)": 6483.1464},
{"time": "22:31:26.91373", "test_id": 342, "iter_cnt": 512, "latency (ms)": 78.581, "throughput (iters/s)": 6515.5699},
{"time": "22:31:26.292179", "test_id": 343, "iter_cnt": 512, "latency (ms)": 79.333, "throughput (iters/s)": 6453.8086},
{"time": "22:31:26.492161", "test_id": 344, "iter_cnt": 512, "latency (ms)": 79.232, "throughput (iters/s)": 6462.0355},
{"time": "22:31:26.691527", "test_id": 345, "iter_cnt": 512, "latency (ms)": 78.515, "throughput (iters/s)": 6521.0469},
{"time": "22:31:26.892145", "test_id": 346, "iter_cnt": 512, "latency (ms)": 79.049, "throughput (iters/s)": 6476.9953},
{"time": "22:31:27.91699", "test_id": 347, "iter_cnt": 512, "latency (ms)": 78.518, "throughput (iters/s)": 6520.7978},
{"time": "22:31:27.292525", "test_id": 348, "iter_cnt": 512, "latency (ms)": 79.256, "throughput (iters/s)": 6460.0787},
{"time": "22:31:27.492397", "test_id": 349, "iter_cnt": 512, "latency (ms)": 79.044, "throughput (iters/s)": 6477.4050},
{"time": "22:31:27.692525", "test_id": 350, "iter_cnt": 512, "latency (ms)": 79.119, "throughput (iters/s)": 6471.2648},
{"time": "22:31:27.891938", "test_id": 351, "iter_cnt": 512, "latency (ms)": 78.445, "throughput (iters/s)": 6526.8660},
{"time": "22:31:28.94381", "test_id": 352, "iter_cnt": 512, "latency (ms)": 80.804, "throughput (iters/s)": 6336.3200},
{"time": "22:31:28.293334", "test_id": 353, "iter_cnt": 512, "latency (ms)": 79.670, "throughput (iters/s)": 6426.5094},
{"time": "22:31:28.492044", "test_id": 354, "iter_cnt": 512, "latency (ms)": 78.328, "throughput (iters/s)": 6536.6153},
{"time": "22:31:28.695652", "test_id": 355, "iter_cnt": 512, "latency (ms)": 81.881, "throughput (iters/s)": 6252.9769},
{"time": "22:31:28.893949", "test_id": 356, "iter_cnt": 512, "latency (ms)": 80.125, "throughput (iters/s)": 6390.0156},
{"time": "22:31:29.92271", "test_id": 357, "iter_cnt": 512, "latency (ms)": 78.394, "throughput (iters/s)": 6531.1121},
{"time": "22:31:29.294968", "test_id": 358, "iter_cnt": 512, "latency (ms)": 81.037, "throughput (iters/s)": 6318.1016},
{"time": "22:31:29.492441", "test_id": 359, "iter_cnt": 512, "latency (ms)": 78.456, "throughput (iters/s)": 6525.9509},
{"time": "22:31:29.694649", "test_id": 360, "iter_cnt": 512, "latency (ms)": 80.577, "throughput (iters/s)": 6354.1705},
{"time": "22:31:29.893637", "test_id": 361, "iter_cnt": 512, "latency (ms)": 79.511, "throughput (iters/s)": 6439.3606},
{"time": "22:31:30.92759", "test_id": 362, "iter_cnt": 512, "latency (ms)": 78.579, "throughput (iters/s)": 6515.7358},
{"time": "22:31:30.294994", "test_id": 363, "iter_cnt": 512, "latency (ms)": 80.761, "throughput (iters/s)": 6339.6937},
{"time": "22:31:30.492725", "test_id": 364, "iter_cnt": 512, "latency (ms)": 78.437, "throughput (iters/s)": 6527.5316},
{"time": "22:31:30.695672", "test_id": 365, "iter_cnt": 512, "latency (ms)": 81.301, "throughput (iters/s)": 6297.5855},
{"time": "22:31:30.893289", "test_id": 366, "iter_cnt": 512, "latency (ms)": 78.833, "throughput (iters/s)": 6494.7420},
{"time": "22:31:31.93391", "test_id": 367, "iter_cnt": 512, "latency (ms)": 78.851, "throughput (iters/s)": 6493.2594},
{"time": "22:31:31.297808", "test_id": 368, "iter_cnt": 512, "latency (ms)": 83.184, "throughput (iters/s)": 6155.0298},
{"time": "22:31:31.495459", "test_id": 369, "iter_cnt": 512, "latency (ms)": 80.750, "throughput (iters/s)": 6340.5573},
{"time": "22:31:31.693324", "test_id": 370, "iter_cnt": 512, "latency (ms)": 78.518, "throughput (iters/s)": 6520.7978},
{"time": "22:31:31.896629", "test_id": 371, "iter_cnt": 512, "latency (ms)": 81.738, "throughput (iters/s)": 6263.9164},
{"time": "22:31:32.93907", "test_id": 372, "iter_cnt": 512, "latency (ms)": 78.961, "throughput (iters/s)": 6484.2137},
{"time": "22:31:32.295138", "test_id": 373, "iter_cnt": 512, "latency (ms)": 80.108, "throughput (iters/s)": 6391.3716},
{"time": "22:31:32.494121", "test_id": 374, "iter_cnt": 512, "latency (ms)": 79.037, "throughput (iters/s)": 6477.9787},
{"time": "22:31:32.694488", "test_id": 375, "iter_cnt": 512, "latency (ms)": 79.350, "throughput (iters/s)": 6452.4260},
{"time": "22:31:32.894893", "test_id": 376, "iter_cnt": 512, "latency (ms)": 79.671, "throughput (iters/s)": 6426.4287},
{"time": "22:31:33.94098", "test_id": 377, "iter_cnt": 512, "latency (ms)": 78.792, "throughput (iters/s)": 6498.1216},
{"time": "22:31:33.295245", "test_id": 378, "iter_cnt": 512, "latency (ms)": 79.853, "throughput (iters/s)": 6411.7816},
{"time": "22:31:33.494974", "test_id": 379, "iter_cnt": 512, "latency (ms)": 79.498, "throughput (iters/s)": 6440.4136},
{"time": "22:31:33.695496", "test_id": 380, "iter_cnt": 512, "latency (ms)": 79.936, "throughput (iters/s)": 6405.1241},
{"time": "22:31:33.894212", "test_id": 381, "iter_cnt": 512, "latency (ms)": 78.567, "throughput (iters/s)": 6516.7309},
{"time": "22:31:34.96392", "test_id": 382, "iter_cnt": 512, "latency (ms)": 80.693, "throughput (iters/s)": 6345.0361},
{"time": "22:31:34.294908", "test_id": 383, "iter_cnt": 512, "latency (ms)": 79.155, "throughput (iters/s)": 6468.3216},
{"time": "22:31:34.495911", "test_id": 384, "iter_cnt": 512, "latency (ms)": 80.104, "throughput (iters/s)": 6391.6908},
{"time": "22:31:34.694931", "test_id": 385, "iter_cnt": 512, "latency (ms)": 79.040, "throughput (iters/s)": 6477.7328},
{"time": "22:31:34.896674", "test_id": 386, "iter_cnt": 512, "latency (ms)": 80.699, "throughput (iters/s)": 6344.5644},
{"time": "22:31:35.94562", "test_id": 387, "iter_cnt": 512, "latency (ms)": 78.498, "throughput (iters/s)": 6522.4592},
{"time": "22:31:35.297816", "test_id": 388, "iter_cnt": 512, "latency (ms)": 81.667, "throughput (iters/s)": 6269.3622},
{"time": "22:31:35.495970", "test_id": 389, "iter_cnt": 512, "latency (ms)": 79.767, "throughput (iters/s)": 6418.6944},
{"time": "22:31:35.695296", "test_id": 390, "iter_cnt": 512, "latency (ms)": 79.006, "throughput (iters/s)": 6480.5205},
{"time": "22:31:35.898710", "test_id": 391, "iter_cnt": 512, "latency (ms)": 82.366, "throughput (iters/s)": 6216.1572},
{"time": "22:31:36.97967", "test_id": 392, "iter_cnt": 512, "latency (ms)": 81.540, "throughput (iters/s)": 6279.1268},
{"time": "22:31:36.296211", "test_id": 393, "iter_cnt": 512, "latency (ms)": 79.699, "throughput (iters/s)": 6424.1709},
{"time": "22:31:36.496448", "test_id": 394, "iter_cnt": 512, "latency (ms)": 79.850, "throughput (iters/s)": 6412.0225},
{"time": "22:31:36.696524", "test_id": 395, "iter_cnt": 512, "latency (ms)": 79.834, "throughput (iters/s)": 6413.3076},
{"time": "22:31:36.896080", "test_id": 396, "iter_cnt": 512, "latency (ms)": 79.310, "throughput (iters/s)": 6455.6802},
{"time": "22:31:37.97228", "test_id": 397, "iter_cnt": 512, "latency (ms)": 80.404, "throughput (iters/s)": 6367.8424},
{"time": "22:31:37.297164", "test_id": 398, "iter_cnt": 512, "latency (ms)": 80.251, "throughput (iters/s)": 6379.9828},
{"time": "22:31:37.497460", "test_id": 399, "iter_cnt": 512, "latency (ms)": 80.461, "throughput (iters/s)": 6363.3313},
{"time": "22:31:37.697532", "test_id": 400, "iter_cnt": 512, "latency (ms)": 80.449, "throughput (iters/s)": 6364.2805},
{"time": "22:31:37.897073", "test_id": 401, "iter_cnt": 512, "latency (ms)": 79.937, "throughput (iters/s)": 6405.0440},
{"time": "22:31:38.98095", "test_id": 402, "iter_cnt": 512, "latency (ms)": 80.871, "throughput (iters/s)": 6331.0705},
{"time": "22:31:38.296937", "test_id": 403, "iter_cnt": 512, "latency (ms)": 79.630, "throughput (iters/s)": 6429.7375},
{"time": "22:31:38.498204", "test_id": 404, "iter_cnt": 512, "latency (ms)": 80.813, "throughput (iters/s)": 6335.6143},
{"time": "22:31:38.697228", "test_id": 405, "iter_cnt": 512, "latency (ms)": 79.749, "throughput (iters/s)": 6420.1432},
{"time": "22:31:38.897660", "test_id": 406, "iter_cnt": 512, "latency (ms)": 80.090, "throughput (iters/s)": 6392.8081},
{"time": "22:31:39.98595", "test_id": 407, "iter_cnt": 512, "latency (ms)": 80.970, "throughput (iters/s)": 6323.3296},
{"time": "22:31:39.296971", "test_id": 408, "iter_cnt": 512, "latency (ms)": 79.263, "throughput (iters/s)": 6459.5082},
{"time": "22:31:39.498827", "test_id": 409, "iter_cnt": 512, "latency (ms)": 81.063, "throughput (iters/s)": 6316.0752},
{"time": "22:31:39.698501", "test_id": 410, "iter_cnt": 512, "latency (ms)": 80.681, "throughput (iters/s)": 6345.9798},
{"time": "22:31:39.897977", "test_id": 411, "iter_cnt": 512, "latency (ms)": 80.102, "throughput (iters/s)": 6391.8504},
{"time": "22:31:40.98008", "test_id": 412, "iter_cnt": 512, "latency (ms)": 80.079, "throughput (iters/s)": 6393.6862},
{"time": "22:31:40.298760", "test_id": 413, "iter_cnt": 512, "latency (ms)": 80.777, "throughput (iters/s)": 6338.4379},
{"time": "22:31:40.497742", "test_id": 414, "iter_cnt": 512, "latency (ms)": 79.704, "throughput (iters/s)": 6423.7679},
{"time": "22:31:40.698813", "test_id": 415, "iter_cnt": 512, "latency (ms)": 80.722, "throughput (iters/s)": 6342.7566},
{"time": "22:31:40.897988", "test_id": 416, "iter_cnt": 512, "latency (ms)": 79.843, "throughput (iters/s)": 6412.5847},
{"time": "22:31:41.98400", "test_id": 417, "iter_cnt": 512, "latency (ms)": 80.170, "throughput (iters/s)": 6386.4288},
{"time": "22:31:41.298015", "test_id": 418, "iter_cnt": 512, "latency (ms)": 79.695, "throughput (iters/s)": 6424.4934},
{"time": "22:31:41.499901", "test_id": 419, "iter_cnt": 512, "latency (ms)": 81.496, "throughput (iters/s)": 6282.5169},
{"time": "22:31:41.699037", "test_id": 420, "iter_cnt": 512, "latency (ms)": 80.547, "throughput (iters/s)": 6356.5372},
{"time": "22:31:41.898703", "test_id": 421, "iter_cnt": 512, "latency (ms)": 80.128, "throughput (iters/s)": 6389.7764},
{"time": "22:31:42.99256", "test_id": 422, "iter_cnt": 512, "latency (ms)": 80.596, "throughput (iters/s)": 6352.6726},
{"time": "22:31:42.299115", "test_id": 423, "iter_cnt": 512, "latency (ms)": 80.401, "throughput (iters/s)": 6368.0800},
{"time": "22:31:42.499215", "test_id": 424, "iter_cnt": 512, "latency (ms)": 80.446, "throughput (iters/s)": 6364.5178},
{"time": "22:31:42.698935", "test_id": 425, "iter_cnt": 512, "latency (ms)": 80.111, "throughput (iters/s)": 6391.1323},
{"time": "22:31:42.899150", "test_id": 426, "iter_cnt": 512, "latency (ms)": 80.273, "throughput (iters/s)": 6378.2343},
{"time": "22:31:43.99507", "test_id": 427, "iter_cnt": 512, "latency (ms)": 80.546, "throughput (iters/s)": 6356.6161},
{"time": "22:31:43.299218", "test_id": 428, "iter_cnt": 512, "latency (ms)": 80.203, "throughput (iters/s)": 6383.8011},
{"time": "22:31:43.498710", "test_id": 429, "iter_cnt": 512, "latency (ms)": 79.607, "throughput (iters/s)": 6431.5952},
{"time": "22:31:43.700374", "test_id": 430, "iter_cnt": 512, "latency (ms)": 81.187, "throughput (iters/s)": 6306.4284},
{"time": "22:31:43.898426", "test_id": 431, "iter_cnt": 512, "latency (ms)": 79.154, "throughput (iters/s)": 6468.4034},
{"time": "22:31:44.101861", "test_id": 432, "iter_cnt": 512, "latency (ms)": 82.506, "throughput (iters/s)": 6205.6093},
{"time": "22:31:44.299432", "test_id": 433, "iter_cnt": 512, "latency (ms)": 80.023, "throughput (iters/s)": 6398.1605},
{"time": "22:31:44.500696", "test_id": 434, "iter_cnt": 512, "latency (ms)": 81.234, "throughput (iters/s)": 6302.7796},
{"time": "22:31:44.700900", "test_id": 435, "iter_cnt": 512, "latency (ms)": 81.348, "throughput (iters/s)": 6293.9470},
{"time": "22:31:44.899160", "test_id": 436, "iter_cnt": 512, "latency (ms)": 79.554, "throughput (iters/s)": 6435.8800},
{"time": "22:31:45.102224", "test_id": 437, "iter_cnt": 512, "latency (ms)": 82.532, "throughput (iters/s)": 6203.6543},
{"time": "22:31:45.300427", "test_id": 438, "iter_cnt": 512, "latency (ms)": 80.651, "throughput (iters/s)": 6348.3404},
{"time": "22:31:45.499276", "test_id": 439, "iter_cnt": 512, "latency (ms)": 79.445, "throughput (iters/s)": 6444.7102},
{"time": "22:31:45.702398", "test_id": 440, "iter_cnt": 512, "latency (ms)": 82.514, "throughput (iters/s)": 6205.0076},
{"time": "22:31:45.900829", "test_id": 441, "iter_cnt": 512, "latency (ms)": 80.891, "throughput (iters/s)": 6329.5051},
{"time": "22:31:46.101198", "test_id": 442, "iter_cnt": 512, "latency (ms)": 81.206, "throughput (iters/s)": 6304.9528},
{"time": "22:31:46.299960", "test_id": 443, "iter_cnt": 512, "latency (ms)": 79.914, "throughput (iters/s)": 6406.8874},
{"time": "22:31:46.501451", "test_id": 444, "iter_cnt": 512, "latency (ms)": 81.321, "throughput (iters/s)": 6296.0367},
{"time": "22:31:46.701751", "test_id": 445, "iter_cnt": 512, "latency (ms)": 81.537, "throughput (iters/s)": 6279.3578},
{"time": "22:31:46.900164", "test_id": 446, "iter_cnt": 512, "latency (ms)": 79.865, "throughput (iters/s)": 6410.8183},
{"time": "22:31:47.100809", "test_id": 447, "iter_cnt": 512, "latency (ms)": 80.456, "throughput (iters/s)": 6363.7268},
{"time": "22:31:47.302281", "test_id": 448, "iter_cnt": 512, "latency (ms)": 81.830, "throughput (iters/s)": 6256.8740},
{"time": "22:31:47.500445", "test_id": 449, "iter_cnt": 512, "latency (ms)": 79.902, "throughput (iters/s)": 6407.8496},
{"time": "22:31:47.701382", "test_id": 450, "iter_cnt": 512, "latency (ms)": 80.757, "throughput (iters/s)": 6340.0077},
{"time": "22:31:47.901479", "test_id": 451, "iter_cnt": 512, "latency (ms)": 80.769, "throughput (iters/s)": 6339.0657},
{"time": "22:31:48.101417", "test_id": 452, "iter_cnt": 512, "latency (ms)": 80.621, "throughput (iters/s)": 6350.7027},
{"time": "22:31:48.302144", "test_id": 453, "iter_cnt": 512, "latency (ms)": 81.265, "throughput (iters/s)": 6300.3753},
{"time": "22:31:48.502599", "test_id": 454, "iter_cnt": 512, "latency (ms)": 81.633, "throughput (iters/s)": 6271.9733},
{"time": "22:31:48.700928", "test_id": 455, "iter_cnt": 512, "latency (ms)": 79.879, "throughput (iters/s)": 6409.6947},
{"time": "22:31:48.902660", "test_id": 456, "iter_cnt": 512, "latency (ms)": 81.523, "throughput (iters/s)": 6280.4362},
{"time": "22:31:49.102566", "test_id": 457, "iter_cnt": 512, "latency (ms)": 81.345, "throughput (iters/s)": 6294.1791},
{"time": "22:31:49.302377", "test_id": 458, "iter_cnt": 512, "latency (ms)": 81.071, "throughput (iters/s)": 6315.4519},
{"time": "22:31:49.500981", "test_id": 459, "iter_cnt": 512, "latency (ms)": 79.621, "throughput (iters/s)": 6430.4643},
{"time": "22:31:49.703117", "test_id": 460, "iter_cnt": 512, "latency (ms)": 81.674, "throughput (iters/s)": 6268.8248},
{"time": "22:31:49.904358", "test_id": 461, "iter_cnt": 512, "latency (ms)": 82.835, "throughput (iters/s)": 6180.9622},
{"time": "22:31:50.102328", "test_id": 462, "iter_cnt": 512, "latency (ms)": 80.752, "throughput (iters/s)": 6340.4002},
{"time": "22:31:50.303593", "test_id": 463, "iter_cnt": 512, "latency (ms)": 81.933, "throughput (iters/s)": 6249.0083},
{"time": "22:31:50.502402", "test_id": 464, "iter_cnt": 512, "latency (ms)": 80.659, "throughput (iters/s)": 6347.7107},
{"time": "22:31:50.701411", "test_id": 465, "iter_cnt": 512, "latency (ms)": 79.584, "throughput (iters/s)": 6433.4540},
{"time": "22:31:50.903671", "test_id": 466, "iter_cnt": 512, "latency (ms)": 81.760, "throughput (iters/s)": 6262.2309},
{"time": "22:31:51.102327", "test_id": 467, "iter_cnt": 512, "latency (ms)": 80.332, "throughput (iters/s)": 6373.5498},
{"time": "22:31:51.302287", "test_id": 468, "iter_cnt": 512, "latency (ms)": 80.237, "throughput (iters/s)": 6381.0960},
{"time": "22:31:51.504388", "test_id": 469, "iter_cnt": 512, "latency (ms)": 82.255, "throughput (iters/s)": 6224.5456},
{"time": "22:31:51.703511", "test_id": 470, "iter_cnt": 512, "latency (ms)": 81.323, "throughput (iters/s)": 6295.8819},
{"time": "22:31:51.903389", "test_id": 471, "iter_cnt": 512, "latency (ms)": 81.117, "throughput (iters/s)": 6311.8705},
{"time": "22:31:52.103548", "test_id": 472, "iter_cnt": 512, "latency (ms)": 81.194, "throughput (iters/s)": 6305.8847},
{"time": "22:31:52.304172", "test_id": 473, "iter_cnt": 512, "latency (ms)": 81.763, "throughput (iters/s)": 6262.0011},
{"time": "22:31:52.502629", "test_id": 474, "iter_cnt": 512, "latency (ms)": 80.165, "throughput (iters/s)": 6386.8272},
{"time": "22:31:52.703682", "test_id": 475, "iter_cnt": 512, "latency (ms)": 81.127, "throughput (iters/s)": 6311.0925},
{"time": "22:31:52.903581", "test_id": 476, "iter_cnt": 512, "latency (ms)": 80.972, "throughput (iters/s)": 6323.1734},
{"time": "22:31:53.103109", "test_id": 477, "iter_cnt": 512, "latency (ms)": 80.415, "throughput (iters/s)": 6366.9713},
{"time": "22:31:53.304836", "test_id": 478, "iter_cnt": 512, "latency (ms)": 82.087, "throughput (iters/s)": 6237.2848},
{"time": "22:31:53.503000", "test_id": 479, "iter_cnt": 512, "latency (ms)": 80.188, "throughput (iters/s)": 6384.9953},
{"time": "22:31:53.705048", "test_id": 480, "iter_cnt": 512, "latency (ms)": 82.152, "throughput (iters/s)": 6232.3498},
{"time": "22:31:53.904239", "test_id": 481, "iter_cnt": 512, "latency (ms)": 81.258, "throughput (iters/s)": 6300.9181},
{"time": "22:31:54.104262", "test_id": 482, "iter_cnt": 512, "latency (ms)": 81.227, "throughput (iters/s)": 6303.3228},
{"time": "22:31:54.304347", "test_id": 483, "iter_cnt": 512, "latency (ms)": 81.257, "throughput (iters/s)": 6300.9956},
{"time": "22:31:54.503870", "test_id": 484, "iter_cnt": 512, "latency (ms)": 80.696, "throughput (iters/s)": 6344.8002},
{"time": "22:31:54.705181", "test_id": 485, "iter_cnt": 512, "latency (ms)": 81.923, "throughput (iters/s)": 6249.7711},
{"time": "22:31:54.904109", "test_id": 486, "iter_cnt": 512, "latency (ms)": 80.763, "throughput (iters/s)": 6339.5367},
{"time": "22:31:55.105004", "test_id": 487, "iter_cnt": 512, "latency (ms)": 81.574, "throughput (iters/s)": 6276.5097},
{"time": "22:31:55.305686", "test_id": 488, "iter_cnt": 512, "latency (ms)": 82.180, "throughput (iters/s)": 6230.2263},
{"time": "22:31:55.504482", "test_id": 489, "iter_cnt": 512, "latency (ms)": 80.891, "throughput (iters/s)": 6329.5051},
{"time": "22:31:55.704258", "test_id": 490, "iter_cnt": 512, "latency (ms)": 80.579, "throughput (iters/s)": 6354.0128},
{"time": "22:31:55.904767", "test_id": 491, "iter_cnt": 512, "latency (ms)": 81.035, "throughput (iters/s)": 6318.2575},
{"time": "22:31:56.104941", "test_id": 492, "iter_cnt": 512, "latency (ms)": 81.124, "throughput (iters/s)": 6311.3259},
{"time": "22:31:56.305122", "test_id": 493, "iter_cnt": 512, "latency (ms)": 81.220, "throughput (iters/s)": 6303.8660},
{"time": "22:31:56.504854", "test_id": 494, "iter_cnt": 512, "latency (ms)": 80.897, "throughput (iters/s)": 6329.0357},
{"time": "22:31:56.704776", "test_id": 495, "iter_cnt": 512, "latency (ms)": 80.731, "throughput (iters/s)": 6342.0495},
{"time": "22:31:56.904778", "test_id": 496, "iter_cnt": 512, "latency (ms)": 80.649, "throughput (iters/s)": 6348.4978},
{"time": "22:31:57.106549", "test_id": 497, "iter_cnt": 512, "latency (ms)": 82.365, "throughput (iters/s)": 6216.2326},
{"time": "22:31:57.306642", "test_id": 498, "iter_cnt": 512, "latency (ms)": 82.405, "throughput (iters/s)": 6213.2152},
{"time": "22:31:57.503896", "test_id": 499, "iter_cnt": 512, "latency (ms)": 79.606, "throughput (iters/s)": 6431.6760},
{"time": "22:31:57.708874", "test_id": 500, "iter_cnt": 512, "latency (ms)": 84.530, "throughput (iters/s)": 6057.0212},
{"time": "22:31:57.906575", "test_id": 501, "iter_cnt": 512, "latency (ms)": 82.146, "throughput (iters/s)": 6232.8050},
{"time": "22:31:58.104534", "test_id": 502, "iter_cnt": 512, "latency (ms)": 80.018, "throughput (iters/s)": 6398.5603},
{"time": "22:31:58.309732", "test_id": 503, "iter_cnt": 512, "latency (ms)": 85.161, "throughput (iters/s)": 6012.1417},
{"time": "22:31:58.507013", "test_id": 504, "iter_cnt": 512, "latency (ms)": 82.388, "throughput (iters/s)": 6214.4973},
{"time": "22:31:58.705724", "test_id": 505, "iter_cnt": 512, "latency (ms)": 81.011, "throughput (iters/s)": 6320.1294},
{"time": "22:31:58.906878", "test_id": 506, "iter_cnt": 512, "latency (ms)": 82.081, "throughput (iters/s)": 6237.7408},
{"time": "22:31:59.105832", "test_id": 507, "iter_cnt": 512, "latency (ms)": 80.981, "throughput (iters/s)": 6322.4707},
{"time": "22:31:59.306840", "test_id": 508, "iter_cnt": 512, "latency (ms)": 81.908, "throughput (iters/s)": 6250.9157},
{"time": "22:31:59.506773", "test_id": 509, "iter_cnt": 512, "latency (ms)": 81.756, "throughput (iters/s)": 6262.5373},
{"time": "22:31:59.705513", "test_id": 510, "iter_cnt": 512, "latency (ms)": 80.441, "throughput (iters/s)": 6364.9134},
{"time": "22:31:59.908379", "test_id": 511, "iter_cnt": 512, "latency (ms)": 83.218, "throughput (iters/s)": 6152.5151},
{"time": "22:32:00.105895", "test_id": 512, "iter_cnt": 512, "latency (ms)": 80.651, "throughput (iters/s)": 6348.3404},
{"time": "22:32:00.307286", "test_id": 513, "iter_cnt": 512, "latency (ms)": 81.958, "throughput (iters/s)": 6247.1022},
{"time": "22:32:00.507444", "test_id": 514, "iter_cnt": 512, "latency (ms)": 82.031, "throughput (iters/s)": 6241.5428},
{"time": "22:32:00.707118", "test_id": 515, "iter_cnt": 512, "latency (ms)": 81.618, "throughput (iters/s)": 6273.1260},
{"time": "22:32:00.907401", "test_id": 516, "iter_cnt": 512, "latency (ms)": 81.854, "throughput (iters/s)": 6255.0395},
{"time": "22:32:01.107093", "test_id": 517, "iter_cnt": 512, "latency (ms)": 81.491, "throughput (iters/s)": 6282.9024},
{"time": "22:32:01.308044", "test_id": 518, "iter_cnt": 512, "latency (ms)": 82.388, "throughput (iters/s)": 6214.4973},
{"time": "22:32:01.507262", "test_id": 519, "iter_cnt": 512, "latency (ms)": 81.552, "throughput (iters/s)": 6278.2029},
{"time": "22:32:01.706833", "test_id": 520, "iter_cnt": 512, "latency (ms)": 81.069, "throughput (iters/s)": 6315.6077},
{"time": "22:32:01.908280", "test_id": 521, "iter_cnt": 512, "latency (ms)": 82.425, "throughput (iters/s)": 6211.7076},
{"time": "22:32:02.107298", "test_id": 522, "iter_cnt": 512, "latency (ms)": 81.389, "throughput (iters/s)": 6290.7764},
{"time": "22:32:02.306822", "test_id": 523, "iter_cnt": 512, "latency (ms)": 80.830, "throughput (iters/s)": 6334.2818},
{"time": "22:32:02.508557", "test_id": 524, "iter_cnt": 512, "latency (ms)": 82.471, "throughput (iters/s)": 6208.2429},
{"time": "22:32:02.707984", "test_id": 525, "iter_cnt": 512, "latency (ms)": 81.816, "throughput (iters/s)": 6257.9447},
{"time": "22:32:02.907954", "test_id": 526, "iter_cnt": 512, "latency (ms)": 81.732, "throughput (iters/s)": 6264.3763},
{"time": "22:32:03.107508", "test_id": 527, "iter_cnt": 512, "latency (ms)": 81.232, "throughput (iters/s)": 6302.9348},
{"time": "22:32:03.307891", "test_id": 528, "iter_cnt": 512, "latency (ms)": 81.559, "throughput (iters/s)": 6277.6640},
{"time": "22:32:03.507715", "test_id": 529, "iter_cnt": 512, "latency (ms)": 81.298, "throughput (iters/s)": 6297.8179},
{"time": "22:32:03.708897", "test_id": 530, "iter_cnt": 512, "latency (ms)": 82.425, "throughput (iters/s)": 6211.7076},
{"time": "22:32:03.907969", "test_id": 531, "iter_cnt": 512, "latency (ms)": 81.444, "throughput (iters/s)": 6286.5282},
{"time": "22:32:04.108033", "test_id": 532, "iter_cnt": 512, "latency (ms)": 81.453, "throughput (iters/s)": 6285.8335},
{"time": "22:32:04.308890", "test_id": 533, "iter_cnt": 512, "latency (ms)": 82.255, "throughput (iters/s)": 6224.5456},
{"time": "22:32:04.507562", "test_id": 534, "iter_cnt": 512, "latency (ms)": 80.843, "throughput (iters/s)": 6333.2632},
{"time": "22:32:04.709311", "test_id": 535, "iter_cnt": 512, "latency (ms)": 82.507, "throughput (iters/s)": 6205.5341},
{"time": "22:32:04.910122", "test_id": 536, "iter_cnt": 512, "latency (ms)": 83.233, "throughput (iters/s)": 6151.4063},
{"time": "22:32:05.108541", "test_id": 537, "iter_cnt": 512, "latency (ms)": 81.568, "throughput (iters/s)": 6276.9714},
{"time": "22:32:05.309770", "test_id": 538, "iter_cnt": 512, "latency (ms)": 82.743, "throughput (iters/s)": 6187.8346},
{"time": "22:32:05.509839", "test_id": 539, "iter_cnt": 512, "latency (ms)": 82.727, "throughput (iters/s)": 6189.0314},
{"time": "22:32:05.707309", "test_id": 540, "iter_cnt": 512, "latency (ms)": 80.112, "throughput (iters/s)": 6391.0525},
{"time": "22:32:05.913979", "test_id": 541, "iter_cnt": 512, "latency (ms)": 86.698, "throughput (iters/s)": 5905.5572},
{"time": "22:32:06.110297", "test_id": 542, "iter_cnt": 512, "latency (ms)": 82.930, "throughput (iters/s)": 6173.8816},
{"time": "22:32:06.309815", "test_id": 543, "iter_cnt": 512, "latency (ms)": 82.393, "throughput (iters/s)": 6214.1201},
{"time": "22:32:06.511314", "test_id": 544, "iter_cnt": 512, "latency (ms)": 83.837, "throughput (iters/s)": 6107.0888},
{"time": "22:32:06.709467", "test_id": 545, "iter_cnt": 512, "latency (ms)": 81.902, "throughput (iters/s)": 6251.3736},
{"time": "22:32:06.908647", "test_id": 546, "iter_cnt": 512, "latency (ms)": 80.967, "throughput (iters/s)": 6323.5639},
{"time": "22:32:07.112085", "test_id": 547, "iter_cnt": 512, "latency (ms)": 84.318, "throughput (iters/s)": 6072.2503},
{"time": "22:32:07.311023", "test_id": 548, "iter_cnt": 512, "latency (ms)": 83.202, "throughput (iters/s)": 6153.6982},
{"time": "22:32:07.507873", "test_id": 549, "iter_cnt": 512, "latency (ms)": 79.998, "throughput (iters/s)": 6400.1600},
{"time": "22:32:07.715735", "test_id": 550, "iter_cnt": 512, "latency (ms)": 87.774, "throughput (iters/s)": 5833.1624},
{"time": "22:32:07.911661", "test_id": 551, "iter_cnt": 512, "latency (ms)": 83.614, "throughput (iters/s)": 6123.3765},
{"time": "22:32:08.108502", "test_id": 552, "iter_cnt": 512, "latency (ms)": 80.371, "throughput (iters/s)": 6370.4570},
{"time": "22:32:08.313523", "test_id": 553, "iter_cnt": 512, "latency (ms)": 85.305, "throughput (iters/s)": 6001.9928},
{"time": "22:32:08.511697", "test_id": 554, "iter_cnt": 512, "latency (ms)": 83.395, "throughput (iters/s)": 6139.4568},
{"time": "22:32:08.710138", "test_id": 555, "iter_cnt": 512, "latency (ms)": 81.753, "throughput (iters/s)": 6262.7671},
{"time": "22:32:08.910678", "test_id": 556, "iter_cnt": 512, "latency (ms)": 82.238, "throughput (iters/s)": 6225.8323},
{"time": "22:32:09.112780", "test_id": 557, "iter_cnt": 512, "latency (ms)": 84.256, "throughput (iters/s)": 6076.7186},
{"time": "22:32:09.310692", "test_id": 558, "iter_cnt": 512, "latency (ms)": 82.114, "throughput (iters/s)": 6235.2339},
{"time": "22:32:09.509783", "test_id": 559, "iter_cnt": 512, "latency (ms)": 81.121, "throughput (iters/s)": 6311.5593},
{"time": "22:32:09.715915", "test_id": 560, "iter_cnt": 512, "latency (ms)": 87.169, "throughput (iters/s)": 5873.6477},
{"time": "22:32:09.911823", "test_id": 561, "iter_cnt": 512, "latency (ms)": 83.023, "throughput (iters/s)": 6166.9658},
{"time": "22:32:10.110365", "test_id": 562, "iter_cnt": 512, "latency (ms)": 81.511, "throughput (iters/s)": 6281.3608},
{"time": "22:32:10.311258", "test_id": 563, "iter_cnt": 512, "latency (ms)": 82.350, "throughput (iters/s)": 6217.3649},
{"time": "22:32:10.512311", "test_id": 564, "iter_cnt": 512, "latency (ms)": 83.321, "throughput (iters/s)": 6144.9094},
{"time": "22:32:10.710842", "test_id": 565, "iter_cnt": 512, "latency (ms)": 81.768, "throughput (iters/s)": 6261.6182},
{"time": "22:32:10.910515", "test_id": 566, "iter_cnt": 512, "latency (ms)": 81.359, "throughput (iters/s)": 6293.0960},
{"time": "22:32:11.112790", "test_id": 567, "iter_cnt": 512, "latency (ms)": 83.550, "throughput (iters/s)": 6128.0670},
{"time": "22:32:11.311713", "test_id": 568, "iter_cnt": 512, "latency (ms)": 82.389, "throughput (iters/s)": 6214.4218},
{"time": "22:32:11.511506", "test_id": 569, "iter_cnt": 512, "latency (ms)": 82.128, "throughput (iters/s)": 6234.1711},
{"time": "22:32:11.712951", "test_id": 570, "iter_cnt": 512, "latency (ms)": 83.489, "throughput (iters/s)": 6132.5444},
{"time": "22:32:11.911635", "test_id": 571, "iter_cnt": 512, "latency (ms)": 82.089, "throughput (iters/s)": 6237.1329},
{"time": "22:32:12.112321", "test_id": 572, "iter_cnt": 512, "latency (ms)": 82.691, "throughput (iters/s)": 6191.7258},
{"time": "22:32:12.312467", "test_id": 573, "iter_cnt": 512, "latency (ms)": 82.753, "throughput (iters/s)": 6187.0869},
{"time": "22:32:12.512074", "test_id": 574, "iter_cnt": 512, "latency (ms)": 82.306, "throughput (iters/s)": 6220.6886},
{"time": "22:32:12.713705", "test_id": 575, "iter_cnt": 512, "latency (ms)": 83.850, "throughput (iters/s)": 6106.1419},
{"time": "22:32:12.912199", "test_id": 576, "iter_cnt": 512, "latency (ms)": 82.291, "throughput (iters/s)": 6221.8226},
{"time": "22:32:13.112013", "test_id": 577, "iter_cnt": 512, "latency (ms)": 82.020, "throughput (iters/s)": 6242.3799},
{"time": "22:32:13.312672", "test_id": 578, "iter_cnt": 512, "latency (ms)": 82.592, "throughput (iters/s)": 6199.1476},
{"time": "22:32:13.513633", "test_id": 579, "iter_cnt": 512, "latency (ms)": 83.469, "throughput (iters/s)": 6134.0138},
{"time": "22:32:13.712632", "test_id": 580, "iter_cnt": 512, "latency (ms)": 82.383, "throughput (iters/s)": 6214.8744},
{"time": "22:32:13.911735", "test_id": 581, "iter_cnt": 512, "latency (ms)": 81.401, "throughput (iters/s)": 6289.8490},
{"time": "22:32:14.114278", "test_id": 582, "iter_cnt": 512, "latency (ms)": 83.861, "throughput (iters/s)": 6105.3410},
